depweaver/__main__.py
depweaver/cli.py
depweaver/resolver.py
depweaver-0.1.1.dist-info/METADATA
depweaver-0.1.1.dist-info/WHEEL
depweaver-0.1.1.dist-info/entry_points.txt
depweaver-0.1.1.dist-info/top_level.txt
depweaver-0.1.1.dist-info/RECORD
