Metadata-Version: 2.4
Name: depweaver
Version: 0.1.1
Summary: A smart dependency resolver for Python data science projects.
Author-email: Joshua Gigo Peter <joshuagigofnaf@gmail.com>
Classifier: Programming Language :: Python :: 3
Classifier: License :: OSI Approved :: MIT License
Classifier: Operating System :: OS Independent
Classifier: Development Status :: 3 - Alpha
Classifier: Intended Audience :: Developers
Requires-Python: >=3.8
Requires-Dist: typer[all]
Requires-Dist: requests
Requires-Dist: packaging
